kprototypes/__init__.py
kprototypes/kprototypes.py
kprototypes/utils.py
kprototypes-0.1.1.dist-info/METADATA
kprototypes-0.1.1.dist-info/WHEEL
kprototypes-0.1.1.dist-info/top_level.txt
kprototypes-0.1.1.dist-info/RECORD
