Metadata-Version: 2.1
Name: kprototypes
Version: 0.1.1
Summary: Implementation of the KPrototypes algorithm using pyspark
Home-page: UNKNOWN
Author: Kawiswara
Author-email: rakha.kawiswara@ddv.id
License: UNKNOWN
Platform: UNKNOWN
Requires-Dist: numpy
